<root>
  <GameObject name="Directional Light" position="(0.0, -21.6, 0.0)" rotation="(0.4, 0.2, -0.1, 0.9)" scale="(1.0, 1.0, 1.0)">
    <Components />
  </GameObject>
  <GameObject name="Main Camera" position="(0.0, 6.4, 19.5)" rotation="(0.0, -1.0, 0.1, 0.0)" scale="(1.0, 1.0, 1.0)">
    <Components />
    <GameObject name="MGECAM" position="(0.0, 0.0, 0.0)" rotation="(0.0, 1.0, 0.0, 0.0)" scale="(1.0, 1.0, 1.0)">
      <Components>
        <CameraComponent FOV="60" aspectRatio="1.333333" nearClipPlane="0.1" farClipPlane="1000" />
      </Components>
    </GameObject>
  </GameObject>
  <GameObject name="model" position="(-3.4, -1.0, 6.0)" rotation="(0.0, 0.0, 0.4, 0.9)" scale="(1.0, 1.0, 1.0)" mesh="model">
    <Components>
      <TestComponent test="15" />
    </Components>
  </GameObject>
  <GameObject name="model" position="(-6.0, 0.0, -6.0)" rotation="(0.0, -0.7, 0.0, 0.7)" scale="(1.0, 1.0, 1.0)" mesh="model">
    <Components>
      <TestComponent test="10" />
      <TestComponent test="20" />
    </Components>
  </GameObject>
  <GameObject name="model" position="(6.0, 0.0, -6.0)" rotation="(0.0, -1.0, 0.0, 0.0)" scale="(1.0, 1.0, 1.0)" mesh="model">
    <Components />
  </GameObject>
  <GameObject name="model" position="(9.7, 0.0, 6.0)" rotation="(0.0, 0.7, 0.0, 0.7)" scale="(1.0, 1.0, 1.0)" mesh="model">
    <Components />
  </GameObject>
  <GameObject name="Cube" position="(-3.8, 0.0, -3.5)" rotation="(0.0, 0.0, 0.0, 1.0)" scale="(1.0, 1.0, 1.0)" mesh="Cube">
    <Components />
    <GameObject name="Cube" position="(0.0, 0.0, 1.9)" rotation="(0.0, 0.0, 0.0, 1.0)" scale="(1.0, 1.0, 1.0)" mesh="Cube">
      <Components />
    </GameObject>
  </GameObject>
  <GameObject name="Sphere" position="(-4.0, 0.0, 3.7)" rotation="(0.0, 0.0, 0.0, 1.0)" scale="(1.0, 1.0, 1.0)" mesh="Sphere">
    <Components />
  </GameObject>
  <GameObject name="Cube" position="(3.6, 0.0, -4.1)" rotation="(0.0, 0.0, 0.0, 1.0)" scale="(1.0, 1.0, 1.0)" mesh="Cube">
    <Components />
  </GameObject>
</root>